infra_deploy/__init__.py
infra_deploy/base.py
infra_deploy/constants.py
infra_deploy/decorators.py
infra_deploy/errors.py
infra_deploy/examples/main.yaml
infra_deploy/experimental/__init__.py
infra_deploy/experimental/standards.py
infra_deploy/helpers.py
infra_deploy/kube_apply.py
infra_deploy/metadata/README.md
infra_deploy/metadata/__init__.py
infra_deploy/metadata/consts.py
infra_deploy/metadata/decorators/__init__.py
infra_deploy/metadata/decorators/ambassador.py
infra_deploy/metadata/decorators/attrs.py
infra_deploy/metadata/decorators/categories.py
infra_deploy/metadata/decorators/contd.py
infra_deploy/metadata/kubevela/README.md
infra_deploy/metadata/kubevela/__init__.py
infra_deploy/metadata/utils.py
infra_deploy/models/__init__.py
infra_deploy/models/_base.py
infra_deploy/models/ambassador/__init__.py
infra_deploy/models/ambassador/mappings.py
infra_deploy/models/ambassador/schemas/auth_service.json
infra_deploy/models/ambassador/schemas/log_service.json
infra_deploy/models/ambassador/schemas/mapping.json
infra_deploy/models/ambassador/schemas/module.json
infra_deploy/models/ambassador/schemas/rate_limit.json
infra_deploy/models/ambassador/schemas/tcp_mapping.json
infra_deploy/models/ambassador/schemas/tls_context.json
infra_deploy/models/ambassador/schemas/tracing_service.json
infra_deploy/models/argocd/__init__.py
infra_deploy/models/argocd/aggregate.py
infra_deploy/models/argocd/chart.py
infra_deploy/models/argocd/core.py
infra_deploy/models/argocd/tasks.py
infra_deploy/models/base.py
infra_deploy/models/claim.py
infra_deploy/models/container.py
infra_deploy/models/deploy.py
infra_deploy/models/enums.py
infra_deploy/models/general.py
infra_deploy/models/labels.py
infra_deploy/models/mem_cpu.py
infra_deploy/models/resources/__init__.py
infra_deploy/models/resources/base.py
infra_deploy/models/service.py
infra_deploy/models/specs.py
infra_deploy/models/volume.py
infra_deploy/typings.py
infra_deploy/utils.py
infra_deploy/validation/__init__.py
infra_deploy-1.0.1.dist-info/WHEEL
infra_deploy-1.0.1.dist-info/METADATA
infra_deploy-1.0.1.dist-info/RECORD
