Metadata-Version: 2.1
Name: infra-deploy
Version: 1.0.1
Summary: 
Author: Kevin Hill
Author-email: kah.kevin.hill@gmail.com
Requires-Python: >=3.8,<4.0
Classifier: Programming Language :: Python :: 3
Classifier: Programming Language :: Python :: 3.8
Classifier: Programming Language :: Python :: 3.9
Requires-Dist: PyYAML (>=5.3.1,<6.0.0)
Requires-Dist: addict (>=2.4.0,<3.0.0)
Requires-Dist: argo-workflows (>=5.0.0,<6.0.0)
Requires-Dist: auto-all (>=1.3.0,<2.0.0)
Requires-Dist: cachetools (>=4.2.0,<5.0.0)
Requires-Dist: confuse (>=1.4.0,<2.0.0)
Requires-Dist: cytoolz (>=0.11.0,<0.12.0)
Requires-Dist: decopatch (>=1.4.8,<2.0.0)
Requires-Dist: decorator (>=4.4.2,<5.0.0)
Requires-Dist: inflection (>=0.5.1,<0.6.0)
Requires-Dist: kubernetes (>=12.0.1,<13.0.0)
Requires-Dist: loguru (>=0.5.3,<0.6.0)
Requires-Dist: makefun (>=1.9.5,<2.0.0)
Requires-Dist: mypy-extensions (>=0.4.3,<0.5.0)
Requires-Dist: orjson (>=3.4.7,<4.0.0)
Requires-Dist: pick (>=1.0.0,<2.0.0)
Requires-Dist: pybase64 (>=1.1.3,<2.0.0)
Requires-Dist: pydantic (>=1.7.3,<2.0.0)
Requires-Dist: varname (>=0.5.6,<0.6.0)
